build/lib/build/lib/build/lib/magLabUtilities/__init__.py
build/lib/build/lib/build/lib/magLabUtilities/cubitutilities/__init__.py
build/lib/build/lib/build/lib/magLabUtilities/datafileutilities/__init__.py
build/lib/build/lib/build/lib/magLabUtilities/exampleUseCases/__init__.py
build/lib/build/lib/build/lib/magLabUtilities/exampleUseCases/topLevelThoughts.py
build/lib/build/lib/build/lib/magLabUtilities/magstromutilities/__init__.py
build/lib/build/lib/build/lib/magLabUtilities/magstromutilities/inputFile.py
build/lib/build/lib/build/lib/magLabUtilities/magstromutilities/modelFile.py
build/lib/build/lib/build/lib/magLabUtilities/magstromutilities/timeDomainSignature.py
build/lib/build/lib/build/lib/magLabUtilities/optimizers/__init__.py
build/lib/build/lib/build/lib/magLabUtilities/optimizers/gradientDescent.py
build/lib/build/lib/build/lib/magLabUtilities/optimizers/particleSwarm.py
build/lib/build/lib/build/lib/magLabUtilities/signalutilities/__init__.py
build/lib/build/lib/build/lib/magLabUtilities/signalutilities/calculus.py
build/lib/build/lib/build/lib/magLabUtilities/signalutilities/interpolation.py
build/lib/build/lib/build/lib/magLabUtilities/signalutilities/signals.py
build/lib/build/lib/build/lib/magLabUtilities/uiutilities/__init__.py
build/lib/build/lib/build/lib/magLabUtilities/uiutilities/messagepipe.py
build/lib/build/lib/magLabUtilities/__init__.py
build/lib/build/lib/magLabUtilities/cubitutilities/__init__.py
build/lib/build/lib/magLabUtilities/datafileutilities/__init__.py
build/lib/build/lib/magLabUtilities/exampleUseCases/__init__.py
build/lib/build/lib/magLabUtilities/exampleUseCases/topLevelThoughts.py
build/lib/build/lib/magLabUtilities/magstromutilities/__init__.py
build/lib/build/lib/magLabUtilities/magstromutilities/inputFile.py
build/lib/build/lib/magLabUtilities/magstromutilities/modelFile.py
build/lib/build/lib/magLabUtilities/magstromutilities/timeDomainSignature.py
build/lib/build/lib/magLabUtilities/optimizers/__init__.py
magLabUtilities-1.2.0.dist-info/LICENSE
magLabUtilities-1.2.0.dist-info/METADATA
magLabUtilities-1.2.0.dist-info/WHEEL
magLabUtilities-1.2.0.dist-info/top_level.txt
magLabUtilities-1.2.0.dist-info/RECORD
